Workbook

Sheet Instrucciones
A1: Matriz de Riesgos de Seguridad de la Información
A2: ISO 27001 Toolkit en español · CC BY-SA 4.0 · github.com/adriangzmncrz-arch/iso27001-toolkit-es
A4: Para qué sirve
A6: Registra el inventario de activos, la evaluación de riesgos y el plan de tratamiento conforme a PRO-01 (cláusulas 6.1.2, 6.1.3, 8.2 y 8.3).
A7: Orden de llenado
A9: 1. Escalas: revisa los criterios. Si cambias los umbrales de nivel de riesgo, cambia también PRO-01.
A10: 2. Inventario de activos: registra los activos dentro del alcance con su propietario y valoración C, I, D (1 a 5).
A11: 3. Evaluación de riesgos: para cada escenario elige activo, amenaza y vulnerabilidad de las listas, asigna probabilidad e impacto inherentes, decide el tratamiento y estima el riesgo residual.
A12: 4. Plan de tratamiento: registra las acciones para cada riesgo que se mitiga, transfiere o evita.
A13: 5. Mapa de calor: se actualiza solo; úsalo en la revisión por la dirección.
A14: Puedes ampliar los catálogos de amenazas y vulnerabilidades agregando filas al final de cada lista; las listas desplegables admiten hasta 200 elementos.
A15: Código de colores
... A19: Las filas incluidas son ejemplos de una PyME de servicios. Bórralas o sustitúyelas por las tuyas (conserva las fórmulas de las columnas grises).

Sheet Inventario de activos
A1: Inventario de activos de información
A2: Control A.5.9 · Valoración de 1 (muy baja) a 5 (muy alta)
A4: ID | B4: Activo | C4: Tipo | D4: Descripción | E4: Propietario | F4: Ubicación | G4: Clasificación | H4: Confidencialidad | I4: Integridad | J4: Disponibilidad | K4: Criticidad (máx. C, I, D) | L4: Proceso | M4: Última revisión
A5: A-001 | B5: Microsoft 365 (correo y colaboración) | C5: Servicio en la nube | D5: Correo, archivos y comunicación interna y con clientes | E5: Responsable de TI | F5: Nube (Microsoft) | G5: Confidencial | H5: 4 | I5: 4 | J5: 4 | K5: =IF(COUNT(H5:J5)=0,"",MAX(H5:J5)) -> 4 | L5: Todos | M5: 2026-10-09
A6: A-002 | B6: CRM | C6: Aplicación | D6: Datos de clientes, prospectos y oportunidades | E6: Director Comercial | F6: Nube (proveedor SaaS) | G6: Confidencial | H6: 4 | I6: 3 | J6: 3 | K6: =IF(COUNT(H6:J6)=0,"",MAX(H6:J6)) -> 4 | L6: Comercialización | M6: 2026-10-09
A7: A-003 | B7: Base de datos del ERP | C7: Información | D7: Facturación, clientes, proveedores y contabilidad | E7: Director de Administración | F7: Nube (AWS) | G7: Restringida | H7: 5 | I7: 5 | J7: 4 | K7: =IF(COUNT(H7:J7)=0,"",MAX(H7:J7)) -> 5 | L7: Administración | M7: 2026-10-09
A8: A-004 | B8: Laptops del personal | C8: Hardware | D8: Equipos de trabajo asignados | E8: Responsable de TI | F8: Oficina / remoto | G8: Uso interno | H8: 3 | I8: 2 | J8: 3 | K8: =IF(COUNT(H8:J8)=0,"",MAX(H8:J8)) -> 3 | L8: Todos | M8: 2026-10-09
A9: A-005 | B9: Repositorios de código fuente | C9: Software | D9: Código de los productos entregados a clientes | E9: Líder de desarrollo | F9: Nube (GitHub) | G9: Confidencial | H9: 4 | I9: 4 | J9: 3 | K9: =IF(COUNT(H9:J9)=0,"",MAX(H9:J9)) -> 4 | L9: Desarrollo | M9: 2026-10-09
K10: =IF(COUNT(H10:J10)=0,"",MAX(H10:J10))
K11: =IF(COUNT(H11:J11)=0,"",MAX(H11:J11))
K12: =IF(COUNT(H12:J12)=0,"",MAX(H12:J12))
K13: =IF(COUNT(H13:J13)=0,"",MAX(H13:J13))
K14: =IF(COUNT(H14:J14)=0,"",MAX(H14:J14))
K15: =IF(COUNT(H15:J15)=0,"",MAX(H15:J15))
K16: =IF(COUNT(H16:J16)=0,"",MAX(H16:J16))
K17: =IF(COUNT(H17:J17)=0,"",MAX(H17:J17))
K18: =IF(COUNT(H18:J18)=0,"",MAX(H18:J18))
K19: =IF(COUNT(H19:J19)=0,"",MAX(H19:J19))
K20: =IF(COUNT(H20:J20)=0,"",MAX(H20:J20))
K21: =IF(COUNT(H21:J21)=0,"",MAX(H21:J21))
... K204: =IF(COUNT(H204:J204)=0,"",MAX(H204:J204))

Sheet Evaluación de riesgos
A1: Evaluación de riesgos
A2: Cláusulas 6.1.2 y 8.2 · Nivel = Probabilidad × Impacto
A4: ID riesgo | B4: ID activo | C4: Activo | D4: ID amenaza | E4: Amenaza | F4: ID vulnerabilidad | G4: Vulnerabilidad | H4: Escenario de riesgo | I4: Dimensión (C, I, D) | J4: Propietario del riesgo | K4: Controles existentes | L4: Probabilidad inherente | M4: Impacto inherente | N4: Nivel inherente | O4: Clasificación inherente | P4: Tratamiento | Q4: Probabilidad residual | R4: Impacto residual | S4: Nivel residual | T4: Clasificación residual | U4: ¿Dentro del apetito? | V4: Fecha de evaluación
A5: R-001 | B5: A-001 | C5: =IF(B5="","",IFERROR(INDEX('Inventario de activos'!$B$5:$B$204,MATCH(B5,'Inventario de activos'!$A$5:$A$204,0)),"ID no encontrado")) -> Microsoft 365 (correo y colaboración) | D5: AM-01 | E5: =IF(D5="","",IFERROR(INDEX('Catálogo de amenazas'!$B$5:$B$204,MATCH(D5,'Catálogo de amenazas'!$A$5:$A$204,0)),"ID no encontrado")) -> Phishing e ingeniería social | F5: VU-03 | G5: =IF(F5="","",IFERROR(INDEX('Catálogo de vulnerabilidades'!$B$5:$B$204,MATCH(F5,'Catálogo de vulnerabilidades'!$A$5:$A$204,0)),"ID no encontrado")) -> Falta de concientización del personal | H5: Por phishing que aprovecha la falta de concientización, podrían comprometerse cuentas de correo y exponerse información de clientes | I5: C, I | J5: Responsable del SGSI | K5: Filtro antispam del proveedor | L5: 4 | M5: 4 | N5: =IF(OR(L5="",M5=""),"",L5*M5) -> 16 | O5: =IF(N5="","",IF(N5>=Escalas!$A$24,"Crítico",IF(N5>=Escalas!$A$23,"Alto",IF(N5>=Escalas!$A$22,"Medio","Bajo")))) -> Crítico | P5: Mitigar | Q5: 2 | R5: 4 | S5: =IF(OR(Q5="",R5=""),"",Q5*R5) -> 8 | T5: =IF(S5="","",IF(S5>=Escalas!$A$24,"Crítico",IF(S5>=Escalas!$A$23,"Alto",IF(S5>=Escalas!$A$22,"Medio","Bajo")))) -> Medio | U5: =IF(S5="","",IF(S5<=Escalas!$D$28,"Sí","No — requiere aprobación")) -> Sí | V5: 2026-10-09
A6: R-002 | B6: A-003 | C6: =IF(B6="","",IFERROR(INDEX('Inventario de activos'!$B$5:$B$204,MATCH(B6,'Inventario de activos'!$A$5:$A$204,0)),"ID no encontrado")) -> Base de datos del ERP | D6: AM-02 | E6: =IF(D6="","",IFERROR(INDEX('Catálogo de amenazas'!$B$5:$B$204,MATCH(D6,'Catálogo de amenazas'!$A$5:$A$204,0)),"ID no encontrado")) -> Ransomware | F6: VU-06 | G6: =IF(F6="","",IFERROR(INDEX('Catálogo de vulnerabilidades'!$B$5:$B$204,MATCH(F6,'Catálogo de vulnerabilidades'!$A$5:$A$204,0)),"ID no encontrado")) -> Respaldos inexistentes, no probados o no aislados | H6: Por ransomware que aprovecha respaldos no aislados, podría cifrarse la base del ERP sin posibilidad de recuperación oportuna | I6: I, D | J6: Director de Administración | K6: Respaldo diario en la misma cuenta de nube | L6: 3 | M6: 5 | N6: =IF(OR(L6="",M6=""),"",L6*M6) -> 15 | O6: =IF(N6="","",IF(N6>=Escalas!$A$24,"Crítico",IF(N6>=Escalas!$A$23,"Alto",IF(N6>=Escalas!$A$22,"Medio","Bajo")))) -> Crítico | P6: Mitigar | Q6: 2 | R6: 3 | S6: =IF(OR(Q6="",R6=""),"",Q6*R6) -> 6 | T6: =IF(S6="","",IF(S6>=Escalas!$A$24,"Crítico",IF(S6>=Escalas!$A$23,"Alto",IF(S6>=Escalas!$A$22,"Medio","Bajo")))) -> Medio | U6: =IF(S6="","",IF(S6<=Escalas!$D$28,"Sí","No — requiere aprobación")) -> Sí | V6: 2026-10-09
A7: R-003 | B7: A-002 | C7: =IF(B7="","",IFERROR(INDEX('Inventario de activos'!$B$5:$B$204,MATCH(B7,'Inventario de activos'!$A$5:$A$204,0)),"ID no encontrado")) -> CRM | D7: AM-06 | E7: =IF(D7="","",IFERROR(INDEX('Catálogo de amenazas'!$B$5:$B$204,MATCH(D7,'Catálogo de amenazas'!$A$5:$A$204,0)),"ID no encontrado")) -> Acceso no autorizado por personal interno o excolaboradores | F7: VU-08 | G7: =IF(F7="","",IFERROR(INDEX('Catálogo de vulnerabilidades'!$B$5:$B$204,MATCH(F7,'Catálogo de vulnerabilidades'!$A$5:$A$204,0)),"ID no encontrado")) -> Proceso de bajas de personal sin control | H7: Por acceso de excolaboradores que aprovecha un proceso de bajas sin control, podría extraerse la cartera de clientes | I7: C | J7: Director Comercial | K7: Baja manual a solicitud de RR. HH. | L7: 3 | M7: 3 | N7: =IF(OR(L7="",M7=""),"",L7*M7) -> 9 | O7: =IF(N7="","",IF(N7>=Escalas!$A$24,"Crítico",IF(N7>=Escalas!$A$23,"Alto",IF(N7>=Escalas!$A$22,"Medio","Bajo")))) -> Alto | P7: Mitigar | Q7: 1 | R7: 3 | S7: =IF(OR(Q7="",R7=""),"",Q7*R7) -> 3 | T7: =IF(S7="","",IF(S7>=Escalas!$A$24,"Crítico",IF(S7>=Escalas!$A$23,"Alto",IF(S7>=Escalas!$A$22,"Medio","Bajo")))) -> Bajo | U7: =IF(S7="","",IF(S7<=Escalas!$D$28,"Sí","No — requiere aprobación")) -> Sí | V7: 2026-10-09
A8: R-004 | B8: A-004 | C8: =IF(B8="","",IFERROR(INDEX('Inventario de activos'!$B$5:$B$204,MATCH(B8,'Inventario de activos'!$A$5:$A$204,0)),"ID no encontrado")) -> Laptops del personal | D8: AM-13 | E8: =IF(D8="","",IFERROR(INDEX('Catálogo de amenazas'!$B$5:$B$204,MATCH(D8,'Catálogo de amenazas'!$A$5:$A$204,0)),"ID no encontrado")) -> Robo o pérdida de equipos | F8: VU-09 | G8: =IF(F8="","",IFERROR(INDEX('Catálogo de vulnerabilidades'!$B$5:$B$204,MATCH(F8,'Catálogo de vulnerabilidades'!$A$5:$A$204,0)),"ID no encontrado")) -> Equipos sin cifrado de disco | H8: Por robo de una laptop sin cifrado, podría divulgarse información de clientes almacenada localmente | I8: C | J8: Responsable de TI | K8: Contraseña de inicio de sesión | L8: 3 | M8: 4 | N8: =IF(OR(L8="",M8=""),"",L8*M8) -> 12 | O8: =IF(N8="","",IF(N8>=Escalas!$A$24,"Crítico",IF(N8>=Escalas!$A$23,"Alto",IF(N8>=Escalas!$A$22,"Medio","Bajo")))) -> Alto | P8: Mitigar | Q8: 3 | R8: 1 | S8: =IF(OR(Q8="",R8=""),"",Q8*R8) -> 3 | T8: =IF(S8="","",IF(S8>=Escalas!$A$24,"Crítico",IF(S8>=Escalas!$A$23,"Alto",IF(S8>=Escalas!$A$22,"Medio","Bajo")))) -> Bajo | U8: =IF(S8="","",IF(S8<=Escalas!$D$28,"Sí","No — requiere aprobación")) -> Sí | V8: 2026-10-09
A9: R-005 | B9: A-001 | C9: =IF(B9="","",IFERROR(INDEX('Inventario de activos'!$B$5:$B$204,MATCH(B9,'Inventario de activos'!$A$5:$A$204,0)),"ID no encontrado")) -> Microsoft 365 (correo y colaboración) | D9: AM-11 | E9: =IF(D9="","",IFERROR(INDEX('Catálogo de amenazas'!$B$5:$B$204,MATCH(D9,'Catálogo de amenazas'!$A$5:$A$204,0)),"ID no encontrado")) -> Falla o interrupción de proveedor o servicio en la nube | F9: VU-13 | G9: =IF(F9="","",IFERROR(INDEX('Catálogo de vulnerabilidades'!$B$5:$B$204,MATCH(F9,'Catálogo de vulnerabilidades'!$A$5:$A$204,0)),"ID no encontrado")) -> Dependencia de un solo proveedor sin plan de salida | H9: Por una interrupción prolongada del proveedor, podría detenerse la comunicación con clientes | I9: D | J9: Responsable de TI | K9: SLA del proveedor | L9: 2 | M9: 4 | N9: =IF(OR(L9="",M9=""),"",L9*M9) -> 8 | O9: =IF(N9="","",IF(N9>=Escalas!$A$24,"Crítico",IF(N9>=Escalas!$A$23,"Alto",IF(N9>=Escalas!$A$22,"Medio","Bajo")))) -> Medio | P9: Aceptar | Q9: 2 | R9: 4 | S9: =IF(OR(Q9="",R9=""),"",Q9*R9) -> 8 | T9: =IF(S9="","",IF(S9>=Escalas!$A$24,"Crítico",IF(S9>=Escalas!$A$23,"Alto",IF(S9>=Escalas!$A$22,"Medio","Bajo")))) -> Medio | U9: =IF(S9="","",IF(S9<=Escalas!$D$28,"Sí","No — requiere aprobación")) -> Sí | V9: 2026-10-09
C10: =IF(B10="","",IFERROR(INDEX('Inventario de activos'!$B$5:$B$204,MATCH(B10,'Inventario de activos'!$A$5:$A$204,0)),"ID no encontrado")) | E10: =IF(D10="","",IFERROR(INDEX('Catálogo de amenazas'!$B$5:$B$204,MATCH(D10,'Catálogo de amenazas'!$A$5:$A$204,0)),"ID no encontrado")) | G10: =IF(F10="","",IFERROR(INDEX('Catálogo de vulnerabilidades'!$B$5:$B$204,MATCH(F10,'Catálogo de vulnerabilidades'!$A$5:$A$204,0)),"ID no encontrado")) | N10: =IF(OR(L10="",M10=""),"",L10*M10) | O10: =IF(N10="","",IF(N10>=Escalas!$A$24,"Crítico",IF(N10>=Escalas!$A$23,"Alto",IF(N10>=Escalas!$A$22,"Medio","Bajo")))) | S10: =IF(OR(Q10="",R10=""),"",Q10*R10) | T10: =IF(S10="","",IF(S10>=Escalas!$A$24,"Crítico",IF(S10>=Escalas!$A$23,"Alto",IF(S10>=Escalas!$A$22,"Medio","Bajo")))) | U10: =IF(S10="","",IF(S10<=Escalas!$D$28,"Sí","No — requiere aprobación"))
C11: =IF(B11="","",IFERROR(INDEX('Inventario de activos'!$B$5:$B$204,MATCH(B11,'Inventario de activos'!$A$5:$A$204,0)),"ID no encontrado")) | E11: =IF(D11="","",IFERROR(INDEX('Catálogo de amenazas'!$B$5:$B$204,MATCH(D11,'Catálogo de amenazas'!$A$5:$A$204,0)),"ID no encontrado")) | G11: =IF(F11="","",IFERROR(INDEX('Catálogo de vulnerabilidades'!$B$5:$B$204,MATCH(F11,'Catálogo de vulnerabilidades'!$A$5:$A$204,0)),"ID no encontrado")) | N11: =IF(OR(L11="",M11=""),"",L11*M11) | O11: =IF(N11="","",IF(N11>=Escalas!$A$24,"Crítico",IF(N11>=Escalas!$A$23,"Alto",IF(N11>=Escalas!$A$22,"Medio","Bajo")))) | S11: =IF(OR(Q11="",R11=""),"",Q11*R11) | T11: =IF(S11="","",IF(S11>=Escalas!$A$24,"Crítico",IF(S11>=Escalas!$A$23,"Alto",IF(S11>=Escalas!$A$22,"Medio","Bajo")))) | U11: =IF(S11="","",IF(S11<=Escalas!$D$28,"Sí","No — requiere aprobación"))
C12: =IF(B12="","",IFERROR(INDEX('Inventario de activos'!$B$5:$B$204,MATCH(B12,'Inventario de activos'!$A$5:$A$204,0)),"ID no encontrado")) | E12: =IF(D12="","",IFERROR(INDEX('Catálogo de amenazas'!$B$5:$B$204,MATCH(D12,'Catálogo de amenazas'!$A$5:$A$204,0)),"ID no encontrado")) | G12: =IF(F12="","",IFERROR(INDEX('Catálogo de vulnerabilidades'!$B$5:$B$204,MATCH(F12,'Catálogo de vulnerabilidades'!$A$5:$A$204,0)),"ID no encontrado")) | N12: =IF(OR(L12="",M12=""),"",L12*M12) | O12: =IF(N12="","",IF(N12>=Escalas!$A$24,"Crítico",IF(N12>=Escalas!$A$23,"Alto",IF(N12>=Escalas!$A$22,"Medio","Bajo")))) | S12: =IF(OR(Q12="",R12=""),"",Q12*R12) | T12: =IF(S12="","",IF(S12>=Escalas!$A$24,"Crítico",IF(S12>=Escalas!$A$23,"Alto",IF(S12>=Escalas!$A$22,"Medio","Bajo")))) | U12: =IF(S12="","",IF(S12<=Escalas!$D$28,"Sí","No — requiere aprobación"))
C13: =IF(B13="","",IFERROR(INDEX('Inventario de activos'!$B$5:$B$204,MATCH(B13,'Inventario de activos'!$A$5:$A$204,0)),"ID no encontrado")) | E13: =IF(D13="","",IFERROR(INDEX('Catálogo de amenazas'!$B$5:$B$204,MATCH(D13,'Catálogo de amenazas'!$A$5:$A$204,0)),"ID no encontrado")) | G13: =IF(F13="","",IFERROR(INDEX('Catálogo de vulnerabilidades'!$B$5:$B$204,MATCH(F13,'Catálogo de vulnerabilidades'!$A$5:$A$204,0)),"ID no encontrado")) | N13: =IF(OR(L13="",M13=""),"",L13*M13) | O13: =IF(N13="","",IF(N13>=Escalas!$A$24,"Crítico",IF(N13>=Escalas!$A$23,"Alto",IF(N13>=Escalas!$A$22,"Medio","Bajo")))) | S13: =IF(OR(Q13="",R13=""),"",Q13*R13) | T13: =IF(S13="","",IF(S13>=Escalas!$A$24,"Crítico",IF(S13>=Escalas!$A$23,"Alto",IF(S13>=Escalas!$A$22,"Medio","Bajo")))) | U13: =IF(S13="","",IF(S13<=Escalas!$D$28,"Sí","No — requiere aprobación"))
C14: =IF(B14="","",IFERROR(INDEX('Inventario de activos'!$B$5:$B$204,MATCH(B14,'Inventario de activos'!$A$5:$A$204,0)),"ID no encontrado")) | E14: =IF(D14="","",IFERROR(INDEX('Catálogo de amenazas'!$B$5:$B$204,MATCH(D14,'Catálogo de amenazas'!$A$5:$A$204,0)),"ID no encontrado")) | G14: =IF(F14="","",IFERROR(INDEX('Catálogo de vulnerabilidades'!$B$5:$B$204,MATCH(F14,'Catálogo de vulnerabilidades'!$A$5:$A$204,0)),"ID no encontrado")) | N14: =IF(OR(L14="",M14=""),"",L14*M14) | O14: =IF(N14="","",IF(N14>=Escalas!$A$24,"Crítico",IF(N14>=Escalas!$A$23,"Alto",IF(N14>=Escalas!$A$22,"Medio","Bajo")))) | S14: =IF(OR(Q14="",R14=""),"",Q14*R14) | T14: =IF(S14="","",IF(S14>=Escalas!$A$24,"Crítico",IF(S14>=Escalas!$A$23,"Alto",IF(S14>=Escalas!$A$22,"Medio","Bajo")))) | U14: =IF(S14="","",IF(S14<=Escalas!$D$28,"Sí","No — requiere aprobación"))
C15: =IF(B15="","",IFERROR(INDEX('Inventario de activos'!$B$5:$B$204,MATCH(B15,'Inventario de activos'!$A$5:$A$204,0)),"ID no encontrado")) | E15: =IF(D15="","",IFERROR(INDEX('Catálogo de amenazas'!$B$5:$B$204,MATCH(D15,'Catálogo de amenazas'!$A$5:$A$204,0)),"ID no encontrado")) | G15: =IF(F15="","",IFERROR(INDEX('Catálogo de vulnerabilidades'!$B$5:$B$204,MATCH(F15,'Catálogo de vulnerabilidades'!$A$5:$A$204,0)),"ID no encontrado")) | N15: =IF(OR(L15="",M15=""),"",L15*M15) | O15: =IF(N15="","",IF(N15>=Escalas!$A$24,"Crítico",IF(N15>=Escalas!$A$23,"Alto",IF(N15>=Escalas!$A$22,"Medio","Bajo")))) | S15: =IF(OR(Q15="",R15=""),"",Q15*R15) | T15: =IF(S15="","",IF(S15>=Escalas!$A$24,"Crítico",IF(S15>=Escalas!$A$23,"Alto",IF(S15>=Escalas!$A$22,"Medio","Bajo")))) | U15: =IF(S15="","",IF(S15<=Escalas!$D$28,"Sí","No — requiere aprobación"))
C16: =IF(B16="","",IFERROR(INDEX('Inventario de activos'!$B$5:$B$204,MATCH(B16,'Inventario de activos'!$A$5:$A$204,0)),"ID no encontrado")) | E16: =IF(D16="","",IFERROR(INDEX('Catálogo de amenazas'!$B$5:$B$204,MATCH(D16,'Catálogo de amenazas'!$A$5:$A$204,0)),"ID no encontrado")) | G16: =IF(F16="","",IFERROR(INDEX('Catálogo de vulnerabilidades'!$B$5:$B$204,MATCH(F16,'Catálogo de vulnerabilidades'!$A$5:$A$204,0)),"ID no encontrado")) | N16: =IF(OR(L16="",M16=""),"",L16*M16) | O16: =IF(N16="","",IF(N16>=Escalas!$A$24,"Crítico",IF(N16>=Escalas!$A$23,"Alto",IF(N16>=Escalas!$A$22,"Medio","Bajo")))) | S16: =IF(OR(Q16="",R16=""),"",Q16*R16) | T16: =IF(S16="","",IF(S16>=Escalas!$A$24,"Crítico",IF(S16>=Escalas!$A$23,"Alto",IF(S16>=Escalas!$A$22,"Medio","Bajo")))) | U16: =IF(S16="","",IF(S16<=Escalas!$D$28,"Sí","No — requiere aprobación"))
C17: =IF(B17="","",IFERROR(INDEX('Inventario de activos'!$B$5:$B$204,MATCH(B17,'Inventario de activos'!$A$5:$A$204,0)),"ID no encontrado")) | E17: =IF(D17="","",IFERROR(INDEX('Catálogo de amenazas'!$B$5:$B$204,MATCH(D17,'Catálogo de amenazas'!$A$5:$A$204,0)),"ID no encontrado")) | G17: =IF(F17="","",IFERROR(INDEX('Catálogo de vulnerabilidades'!$B$5:$B$204,MATCH(F17,'Catálogo de vulnerabilidades'!$A$5:$A$204,0)),"ID no encontrado")) | N17: =IF(OR(L17="",M17=""),"",L17*M17) | O17: =IF(N17="","",IF(N17>=Escalas!$A$24,"Crítico",IF(N17>=Escalas!$A$23,"Alto",IF(N17>=Escalas!$A$22,"Medio","Bajo")))) | S17: =IF(OR(Q17="",R17=""),"",Q17*R17) | T17: =IF(S17="","",IF(S17>=Escalas!$A$24,"Crítico",IF(S17>=Escalas!$A$23,"Alto",IF(S17>=Escalas!$A$22,"Medio","Bajo")))) | U17: =IF(S17="","",IF(S17<=Escalas!$D$28,"Sí","No — requiere aprobación"))
C18: =IF(B18="","",IFERROR(INDEX('Inventario de activos'!$B$5:$B$204,MATCH(B18,'Inventario de activos'!$A$5:$A$204,0)),"ID no encontrado")) | E18: =IF(D18="","",IFERROR(INDEX('Catálogo de amenazas'!$B$5:$B$204,MATCH(D18,'Catálogo de amenazas'!$A$5:$A$204,0)),"ID no encontrado")) | G18: =IF(F18="","",IFERROR(INDEX('Catálogo de vulnerabilidades'!$B$5:$B$204,MATCH(F18,'Catálogo de vulnerabilidades'!$A$5:$A$204,0)),"ID no encontrado")) | N18: =IF(OR(L18="",M18=""),"",L18*M18) | O18: =IF(N18="","",IF(N18>=Escalas!$A$24,"Crítico",IF(N18>=Escalas!$A$23,"Alto",IF(N18>=Escalas!$A$22,"Medio","Bajo")))) | S18: =IF(OR(Q18="",R18=""),"",Q18*R18) | T18: =IF(S18="","",IF(S18>=Escalas!$A$24,"Crítico",IF(S18>=Escalas!$A$23,"Alto",IF(S18>=Escalas!$A$22,"Medio","Bajo")))) | U18: =IF(S18="","",IF(S18<=Escalas!$D$28,"Sí","No — requiere aprobación"))
C19: =IF(B19="","",IFERROR(INDEX('Inventario de activos'!$B$5:$B$204,MATCH(B19,'Inventario de activos'!$A$5:$A$204,0)),"ID no encontrado")) | E19: =IF(D19="","",IFERROR(INDEX('Catálogo de amenazas'!$B$5:$B$204,MATCH(D19,'Catálogo de amenazas'!$A$5:$A$204,0)),"ID no encontrado")) | G19: =IF(F19="","",IFERROR(INDEX('Catálogo de vulnerabilidades'!$B$5:$B$204,MATCH(F19,'Catálogo de vulnerabilidades'!$A$5:$A$204,0)),"ID no encontrado")) | N19: =IF(OR(L19="",M19=""),"",L19*M19) | O19: =IF(N19="","",IF(N19>=Escalas!$A$24,"Crítico",IF(N19>=Escalas!$A$23,"Alto",IF(N19>=Escalas!$A$22,"Medio","Bajo")))) | S19: =IF(OR(Q19="",R19=""),"",Q19*R19) | T19: =IF(S19="","",IF(S19>=Escalas!$A$24,"Crítico",IF(S19>=Escalas!$A$23,"Alto",IF(S19>=Escalas!$A$22,"Medio","Bajo")))) | U19: =IF(S19="","",IF(S19<=Escalas!$D$28,"Sí","No — requiere aprobación"))
C20: =IF(B20="","",IFERROR(INDEX('Inventario de activos'!$B$5:$B$204,MATCH(B20,'Inventario de activos'!$A$5:$A$204,0)),"ID no encontrado")) | E20: =IF(D20="","",IFERROR(INDEX('Catálogo de amenazas'!$B$5:$B$204,MATCH(D20,'Catálogo de amenazas'!$A$5:$A$204,0)),"ID no encontrado")) | G20: =IF(F20="","",IFERROR(INDEX('Catálogo de vulnerabilidades'!$B$5:$B$204,MATCH(F20,'Catálogo de vulnerabilidades'!$A$5:$A$204,0)),"ID no encontrado")) | N20: =IF(OR(L20="",M20=""),"",L20*M20) | O20: =IF(N20="","",IF(N20>=Escalas!$A$24,"Crítico",IF(N20>=Escalas!$A$23,"Alto",IF(N20>=Escalas!$A$22,"Medio","Bajo")))) | S20: =IF(OR(Q20="",R20=""),"",Q20*R20) | T20: =IF(S20="","",IF(S20>=Escalas!$A$24,"Crítico",IF(S20>=Escalas!$A$23,"Alto",IF(S20>=Escalas!$A$22,"Medio","Bajo")))) | U20: =IF(S20="","",IF(S20<=Escalas!$D$28,"Sí","No — requiere aprobación"))
C21: =IF(B21="","",IFERROR(INDEX('Inventario de activos'!$B$5:$B$204,MATCH(B21,'Inventario de activos'!$A$5:$A$204,0)),"ID no encontrado")) | E21: =IF(D21="","",IFERROR(INDEX('Catálogo de amenazas'!$B$5:$B$204,MATCH(D21,'Catálogo de amenazas'!$A$5:$A$204,0)),"ID no encontrado")) | G21: =IF(F21="","",IFERROR(INDEX('Catálogo de vulnerabilidades'!$B$5:$B$204,MATCH(F21,'Catálogo de vulnerabilidades'!$A$5:$A$204,0)),"ID no encontrado")) | N21: =IF(OR(L21="",M21=""),"",L21*M21) | O21: =IF(N21="","",IF(N21>=Escalas!$A$24,"Crítico",IF(N21>=Escalas!$A$23,"Alto",IF(N21>=Escalas!$A$22,"Medio","Bajo")))) | S21: =IF(OR(Q21="",R21=""),"",Q21*R21) | T21: =IF(S21="","",IF(S21>=Escalas!$A$24,"Crítico",IF(S21>=Escalas!$A$23,"Alto",IF(S21>=Escalas!$A$22,"Medio","Bajo")))) | U21: =IF(S21="","",IF(S21<=Escalas!$D$28,"Sí","No — requiere aprobación"))
... C204: =IF(B204="","",IFERROR(INDEX('Inventario de activos'!$B$5:$B$204,MATCH(B204,'Inventario de activos'!$A$5:$A$204,0)),"ID no encontrado")) | E204: =IF(D204="","",IFERROR(INDEX('Catálogo de amenazas'!$B$5:$B$204,MATCH(D204,'Catálogo de amenazas'!$A$5:$A$204,0)),"ID no encontrado")) | G204: =IF(F204="","",IFERROR(INDEX('Catálogo de vulnerabilidades'!$B$5:$B$204,MATCH(F204,'Catálogo de vulnerabilidades'!$A$5:$A$204,0)),"ID no encontrado")) | N204: =IF(OR(L204="",M204=""),"",L204*M204) | O204: =IF(N204="","",IF(N204>=Escalas!$A$24,"Crítico",IF(N204>=Escalas!$A$23,"Alto",IF(N204>=Escalas!$A$22,"Medio","Bajo")))) | S204: =IF(OR(Q204="",R204=""),"",Q204*R204) | T204: =IF(S204="","",IF(S204>=Escalas!$A$24,"Crítico",IF(S204>=Escalas!$A$23,"Alto",IF(S204>=Escalas!$A$22,"Medio","Bajo")))) | U204: =IF(S204="","",IF(S204<=Escalas!$D$28,"Sí","No — requiere aprobación"))

Sheet Plan de tratamiento
A1: Plan de tratamiento de riesgos
A2: Cláusulas 6.1.3 y 8.3
A4: ID acción | B4: ID riesgo | C4: Escenario de riesgo | D4: Nivel inherente | E4: Acción o control a implementar | F4: Controles del Anexo A | G4: Responsable | H4: Recursos | I4: Fecha de inicio | J4: Fecha compromiso | K4: Estado | L4: % de avance | M4: ¿Vencida? | N4: Comentarios
A5: T-001 | B5: R-001 | C5: =IF(B5="","",IFERROR(INDEX('Evaluación de riesgos'!$H$5:$H$204,MATCH(B5,'Evaluación de riesgos'!$A$5:$A$204,0)),"ID no encontrado")) -> Por phishing que aprovecha la falta de concientización, podrían comprometerse cuentas de correo y exponerse información de clientes | D5: =IF(B5="","",IFERROR(INDEX('Evaluación de riesgos'!$O$5:$O$204,MATCH(B5,'Evaluación de riesgos'!$A$5:$A$204,0)),"")) -> Crítico | E5: Habilitar MFA para el 100 % de las cuentas y simulaciones de phishing trimestrales | F5: A.5.17, A.8.5, A.6.3 | G5: Responsable de TI | H5: Licencias existentes; plataforma de simulación | I5: 46204 | J5: 46371 | K5: En curso | L5: 0.5 | M5: =IF(OR(J5="",K5="Completada",K5="Cancelada"),"",IF(J5<TODAY(),"Sí","No")) -> No
A6: T-002 | B6: R-002 | C6: =IF(B6="","",IFERROR(INDEX('Evaluación de riesgos'!$H$5:$H$204,MATCH(B6,'Evaluación de riesgos'!$A$5:$A$204,0)),"ID no encontrado")) -> Por ransomware que aprovecha respaldos no aislados, podría cifrarse la base del ERP sin posibilidad de recuperación oportuna | D6: =IF(B6="","",IFERROR(INDEX('Evaluación de riesgos'!$O$5:$O$204,MATCH(B6,'Evaluación de riesgos'!$A$5:$A$204,0)),"")) -> Crítico | E6: Implementar respaldo inmutable en cuenta separada (3-2-1-1-0) y prueba semestral de restauración | F6: A.8.13 | G6: Responsable de TI | H6: Servicio de respaldo inmutable | I6: 46235 | J6: 46418 | K6: Planificada | L6: 0 | M6: =IF(OR(J6="",K6="Completada",K6="Cancelada"),"",IF(J6<TODAY(),"Sí","No")) -> No
A7: T-003 | B7: R-003 | C7: =IF(B7="","",IFERROR(INDEX('Evaluación de riesgos'!$H$5:$H$204,MATCH(B7,'Evaluación de riesgos'!$A$5:$A$204,0)),"ID no encontrado")) -> Por acceso de excolaboradores que aprovecha un proceso de bajas sin control, podría extraerse la cartera de clientes | D7: =IF(B7="","",IFERROR(INDEX('Evaluación de riesgos'!$O$5:$O$204,MATCH(B7,'Evaluación de riesgos'!$A$5:$A$204,0)),"")) -> Alto | E7: Implementar PRO-07 e integrar el CRM al inicio de sesión único | F7: A.5.18, A.6.5 | G7: Responsable de TI | H7: Horas internas | I7: 46174 | J7: 46295 | K7: Completada | L7: 1 | M7: =IF(OR(J7="",K7="Completada",K7="Cancelada"),"",IF(J7<TODAY(),"Sí","No"))
A8: T-004 | B8: R-004 | C8: =IF(B8="","",IFERROR(INDEX('Evaluación de riesgos'!$H$5:$H$204,MATCH(B8,'Evaluación de riesgos'!$A$5:$A$204,0)),"ID no encontrado")) -> Por robo de una laptop sin cifrado, podría divulgarse información de clientes almacenada localmente | D8: =IF(B8="","",IFERROR(INDEX('Evaluación de riesgos'!$O$5:$O$204,MATCH(B8,'Evaluación de riesgos'!$A$5:$A$204,0)),"")) -> Alto | E8: Cifrado de disco gestionado por MDM en todas las laptops | F8: A.8.1, A.8.24 | G8: Responsable de TI | H8: Licencias MDM | I8: 46143 | J8: 46265 | K8: Completada | L8: 1 | M8: =IF(OR(J8="",K8="Completada",K8="Cancelada"),"",IF(J8<TODAY(),"Sí","No"))
C9: =IF(B9="","",IFERROR(INDEX('Evaluación de riesgos'!$H$5:$H$204,MATCH(B9,'Evaluación de riesgos'!$A$5:$A$204,0)),"ID no encontrado")) | D9: =IF(B9="","",IFERROR(INDEX('Evaluación de riesgos'!$O$5:$O$204,MATCH(B9,'Evaluación de riesgos'!$A$5:$A$204,0)),"")) | M9: =IF(OR(J9="",K9="Completada",K9="Cancelada"),"",IF(J9<TODAY(),"Sí","No"))
C10: =IF(B10="","",IFERROR(INDEX('Evaluación de riesgos'!$H$5:$H$204,MATCH(B10,'Evaluación de riesgos'!$A$5:$A$204,0)),"ID no encontrado")) | D10: =IF(B10="","",IFERROR(INDEX('Evaluación de riesgos'!$O$5:$O$204,MATCH(B10,'Evaluación de riesgos'!$A$5:$A$204,0)),"")) | M10: =IF(OR(J10="",K10="Completada",K10="Cancelada"),"",IF(J10<TODAY(),"Sí","No"))
C11: =IF(B11="","",IFERROR(INDEX('Evaluación de riesgos'!$H$5:$H$204,MATCH(B11,'Evaluación de riesgos'!$A$5:$A$204,0)),"ID no encontrado")) | D11: =IF(B11="","",IFERROR(INDEX('Evaluación de riesgos'!$O$5:$O$204,MATCH(B11,'Evaluación de riesgos'!$A$5:$A$204,0)),"")) | M11: =IF(OR(J11="",K11="Completada",K11="Cancelada"),"",IF(J11<TODAY(),"Sí","No"))
C12: =IF(B12="","",IFERROR(INDEX('Evaluación de riesgos'!$H$5:$H$204,MATCH(B12,'Evaluación de riesgos'!$A$5:$A$204,0)),"ID no encontrado")) | D12: =IF(B12="","",IFERROR(INDEX('Evaluación de riesgos'!$O$5:$O$204,MATCH(B12,'Evaluación de riesgos'!$A$5:$A$204,0)),"")) | M12: =IF(OR(J12="",K12="Completada",K12="Cancelada"),"",IF(J12<TODAY(),"Sí","No"))
C13: =IF(B13="","",IFERROR(INDEX('Evaluación de riesgos'!$H$5:$H$204,MATCH(B13,'Evaluación de riesgos'!$A$5:$A$204,0)),"ID no encontrado")) | D13: =IF(B13="","",IFERROR(INDEX('Evaluación de riesgos'!$O$5:$O$204,MATCH(B13,'Evaluación de riesgos'!$A$5:$A$204,0)),"")) | M13: =IF(OR(J13="",K13="Completada",K13="Cancelada"),"",IF(J13<TODAY(),"Sí","No"))
C14: =IF(B14="","",IFERROR(INDEX('Evaluación de riesgos'!$H$5:$H$204,MATCH(B14,'Evaluación de riesgos'!$A$5:$A$204,0)),"ID no encontrado")) | D14: =IF(B14="","",IFERROR(INDEX('Evaluación de riesgos'!$O$5:$O$204,MATCH(B14,'Evaluación de riesgos'!$A$5:$A$204,0)),"")) | M14: =IF(OR(J14="",K14="Completada",K14="Cancelada"),"",IF(J14<TODAY(),"Sí","No"))
C15: =IF(B15="","",IFERROR(INDEX('Evaluación de riesgos'!$H$5:$H$204,MATCH(B15,'Evaluación de riesgos'!$A$5:$A$204,0)),"ID no encontrado")) | D15: =IF(B15="","",IFERROR(INDEX('Evaluación de riesgos'!$O$5:$O$204,MATCH(B15,'Evaluación de riesgos'!$A$5:$A$204,0)),"")) | M15: =IF(OR(J15="",K15="Completada",K15="Cancelada"),"",IF(J15<TODAY(),"Sí","No"))
C16: =IF(B16="","",IFERROR(INDEX('Evaluación de riesgos'!$H$5:$H$204,MATCH(B16,'Evaluación de riesgos'!$A$5:$A$204,0)),"ID no encontrado")) | D16: =IF(B16="","",IFERROR(INDEX('Evaluación de riesgos'!$O$5:$O$204,MATCH(B16,'Evaluación de riesgos'!$A$5:$A$204,0)),"")) | M16: =IF(OR(J16="",K16="Completada",K16="Cancelada"),"",IF(J16<TODAY(),"Sí","No"))
C17: =IF(B17="","",IFERROR(INDEX('Evaluación de riesgos'!$H$5:$H$204,MATCH(B17,'Evaluación de riesgos'!$A$5:$A$204,0)),"ID no encontrado")) | D17: =IF(B17="","",IFERROR(INDEX('Evaluación de riesgos'!$O$5:$O$204,MATCH(B17,'Evaluación de riesgos'!$A$5:$A$204,0)),"")) | M17: =IF(OR(J17="",K17="Completada",K17="Cancelada"),"",IF(J17<TODAY(),"Sí","No"))
C18: =IF(B18="","",IFERROR(INDEX('Evaluación de riesgos'!$H$5:$H$204,MATCH(B18,'Evaluación de riesgos'!$A$5:$A$204,0)),"ID no encontrado")) | D18: =IF(B18="","",IFERROR(INDEX('Evaluación de riesgos'!$O$5:$O$204,MATCH(B18,'Evaluación de riesgos'!$A$5:$A$204,0)),"")) | M18: =IF(OR(J18="",K18="Completada",K18="Cancelada"),"",IF(J18<TODAY(),"Sí","No"))
C19: =IF(B19="","",IFERROR(INDEX('Evaluación de riesgos'!$H$5:$H$204,MATCH(B19,'Evaluación de riesgos'!$A$5:$A$204,0)),"ID no encontrado")) | D19: =IF(B19="","",IFERROR(INDEX('Evaluación de riesgos'!$O$5:$O$204,MATCH(B19,'Evaluación de riesgos'!$A$5:$A$204,0)),"")) | M19: =IF(OR(J19="",K19="Completada",K19="Cancelada"),"",IF(J19<TODAY(),"Sí","No"))
C20: =IF(B20="","",IFERROR(INDEX('Evaluación de riesgos'!$H$5:$H$204,MATCH(B20,'Evaluación de riesgos'!$A$5:$A$204,0)),"ID no encontrado")) | D20: =IF(B20="","",IFERROR(INDEX('Evaluación de riesgos'!$O$5:$O$204,MATCH(B20,'Evaluación de riesgos'!$A$5:$A$204,0)),"")) | M20: =IF(OR(J20="",K20="Completada",K20="Cancelada"),"",IF(J20<TODAY(),"Sí","No"))
... C204: =IF(B204="","",IFERROR(INDEX('Evaluación de riesgos'!$H$5:$H$204,MATCH(B204,'Evaluación de riesgos'!$A$5:$A$204,0)),"ID no encontrado")) | D204: =IF(B204="","",IFERROR(INDEX('Evaluación de riesgos'!$O$5:$O$204,MATCH(B204,'Evaluación de riesgos'!$A$5:$A$204,0)),"")) | M204: =IF(OR(J204="",K204="Completada",K204="Cancelada"),"",IF(J204<TODAY(),"Sí","No"))

Sheet Mapa de calor
A1: Mapa de calor
A2: Número de riesgos en cada combinación de probabilidad e impacto. Se actualiza automáticamente.
A4: Riesgo inherente | H4: Riesgo residual
A5: Prob. ↓ Imp. → | B5: 1 | C5: 2 | D5: 3 | E5: 4 | F5: 5 | H5: Prob. ↓ Imp. → | I5: 1 | J5: 2 | K5: 3 | L5: 4 | M5: 5
A6: 5 | B6: =COUNTIFS('Evaluación de riesgos'!$L$5:$L$204,5,'Evaluación de riesgos'!$M$5:$M$204,1) -> 0 | C6: =COUNTIFS('Evaluación de riesgos'!$L$5:$L$204,5,'Evaluación de riesgos'!$M$5:$M$204,2) -> 0 | D6: =COUNTIFS('Evaluación de riesgos'!$L$5:$L$204,5,'Evaluación de riesgos'!$M$5:$M$204,3) -> 0 | E6: =COUNTIFS('Evaluación de riesgos'!$L$5:$L$204,5,'Evaluación de riesgos'!$M$5:$M$204,4) -> 0 | F6: =COUNTIFS('Evaluación de riesgos'!$L$5:$L$204,5,'Evaluación de riesgos'!$M$5:$M$204,5) -> 0 | H6: 5 | I6: =COUNTIFS('Evaluación de riesgos'!$Q$5:$Q$204,5,'Evaluación de riesgos'!$R$5:$R$204,1) -> 0 | J6: =COUNTIFS('Evaluación de riesgos'!$Q$5:$Q$204,5,'Evaluación de riesgos'!$R$5:$R$204,2) -> 0 | K6: =COUNTIFS('Evaluación de riesgos'!$Q$5:$Q$204,5,'Evaluación de riesgos'!$R$5:$R$204,3) -> 0 | L6: =COUNTIFS('Evaluación de riesgos'!$Q$5:$Q$204,5,'Evaluación de riesgos'!$R$5:$R$204,4) -> 0 | M6: =COUNTIFS('Evaluación de riesgos'!$Q$5:$Q$204,5,'Evaluación de riesgos'!$R$5:$R$204,5) -> 0
A7: 4 | B7: =COUNTIFS('Evaluación de riesgos'!$L$5:$L$204,4,'Evaluación de riesgos'!$M$5:$M$204,1) -> 0 | C7: =COUNTIFS('Evaluación de riesgos'!$L$5:$L$204,4,'Evaluación de riesgos'!$M$5:$M$204,2) -> 0 | D7: =COUNTIFS('Evaluación de riesgos'!$L$5:$L$204,4,'Evaluación de riesgos'!$M$5:$M$204,3) -> 0 | E7: =COUNTIFS('Evaluación de riesgos'!$L$5:$L$204,4,'Evaluación de riesgos'!$M$5:$M$204,4) -> 1 | F7: =COUNTIFS('Evaluación de riesgos'!$L$5:$L$204,4,'Evaluación de riesgos'!$M$5:$M$204,5) -> 0 | H7: 4 | I7: =COUNTIFS('Evaluación de riesgos'!$Q$5:$Q$204,4,'Evaluación de riesgos'!$R$5:$R$204,1) -> 0 | J7: =COUNTIFS('Evaluación de riesgos'!$Q$5:$Q$204,4,'Evaluación de riesgos'!$R$5:$R$204,2) -> 0 | K7: =COUNTIFS('Evaluación de riesgos'!$Q$5:$Q$204,4,'Evaluación de riesgos'!$R$5:$R$204,3) -> 0 | L7: =COUNTIFS('Evaluación de riesgos'!$Q$5:$Q$204,4,'Evaluación de riesgos'!$R$5:$R$204,4) -> 0 | M7: =COUNTIFS('Evaluación de riesgos'!$Q$5:$Q$204,4,'Evaluación de riesgos'!$R$5:$R$204,5) -> 0
A8: 3 | B8: =COUNTIFS('Evaluación de riesgos'!$L$5:$L$204,3,'Evaluación de riesgos'!$M$5:$M$204,1) -> 0 | C8: =COUNTIFS('Evaluación de riesgos'!$L$5:$L$204,3,'Evaluación de riesgos'!$M$5:$M$204,2) -> 0 | D8: =COUNTIFS('Evaluación de riesgos'!$L$5:$L$204,3,'Evaluación de riesgos'!$M$5:$M$204,3) -> 1 | E8: =COUNTIFS('Evaluación de riesgos'!$L$5:$L$204,3,'Evaluación de riesgos'!$M$5:$M$204,4) -> 1 | F8: =COUNTIFS('Evaluación de riesgos'!$L$5:$L$204,3,'Evaluación de riesgos'!$M$5:$M$204,5) -> 1 | H8: 3 | I8: =COUNTIFS('Evaluación de riesgos'!$Q$5:$Q$204,3,'Evaluación de riesgos'!$R$5:$R$204,1) -> 1 | J8: =COUNTIFS('Evaluación de riesgos'!$Q$5:$Q$204,3,'Evaluación de riesgos'!$R$5:$R$204,2) -> 0 | K8: =COUNTIFS('Evaluación de riesgos'!$Q$5:$Q$204,3,'Evaluación de riesgos'!$R$5:$R$204,3) -> 0 | L8: =COUNTIFS('Evaluación de riesgos'!$Q$5:$Q$204,3,'Evaluación de riesgos'!$R$5:$R$204,4) -> 0 | M8: =COUNTIFS('Evaluación de riesgos'!$Q$5:$Q$204,3,'Evaluación de riesgos'!$R$5:$R$204,5) -> 0
A9: 2 | B9: =COUNTIFS('Evaluación de riesgos'!$L$5:$L$204,2,'Evaluación de riesgos'!$M$5:$M$204,1) -> 0 | C9: =COUNTIFS('Evaluación de riesgos'!$L$5:$L$204,2,'Evaluación de riesgos'!$M$5:$M$204,2) -> 0 | D9: =COUNTIFS('Evaluación de riesgos'!$L$5:$L$204,2,'Evaluación de riesgos'!$M$5:$M$204,3) -> 0 | E9: =COUNTIFS('Evaluación de riesgos'!$L$5:$L$204,2,'Evaluación de riesgos'!$M$5:$M$204,4) -> 1 | F9: =COUNTIFS('Evaluación de riesgos'!$L$5:$L$204,2,'Evaluación de riesgos'!$M$5:$M$204,5) -> 0 | H9: 2 | I9: =COUNTIFS('Evaluación de riesgos'!$Q$5:$Q$204,2,'Evaluación de riesgos'!$R$5:$R$204,1) -> 0 | J9: =COUNTIFS('Evaluación de riesgos'!$Q$5:$Q$204,2,'Evaluación de riesgos'!$R$5:$R$204,2) -> 0 | K9: =COUNTIFS('Evaluación de riesgos'!$Q$5:$Q$204,2,'Evaluación de riesgos'!$R$5:$R$204,3) -> 1 | L9: =COUNTIFS('Evaluación de riesgos'!$Q$5:$Q$204,2,'Evaluación de riesgos'!$R$5:$R$204,4) -> 2 | M9: =COUNTIFS('Evaluación de riesgos'!$Q$5:$Q$204,2,'Evaluación de riesgos'!$R$5:$R$204,5) -> 0
A10: 1 | B10: =COUNTIFS('Evaluación de riesgos'!$L$5:$L$204,1,'Evaluación de riesgos'!$M$5:$M$204,1) -> 0 | C10: =COUNTIFS('Evaluación de riesgos'!$L$5:$L$204,1,'Evaluación de riesgos'!$M$5:$M$204,2) -> 0 | D10: =COUNTIFS('Evaluación de riesgos'!$L$5:$L$204,1,'Evaluación de riesgos'!$M$5:$M$204,3) -> 0 | E10: =COUNTIFS('Evaluación de riesgos'!$L$5:$L$204,1,'Evaluación de riesgos'!$M$5:$M$204,4) -> 0 | F10: =COUNTIFS('Evaluación de riesgos'!$L$5:$L$204,1,'Evaluación de riesgos'!$M$5:$M$204,5) -> 0 | H10: 1 | I10: =COUNTIFS('Evaluación de riesgos'!$Q$5:$Q$204,1,'Evaluación de riesgos'!$R$5:$R$204,1) -> 0 | J10: =COUNTIFS('Evaluación de riesgos'!$Q$5:$Q$204,1,'Evaluación de riesgos'!$R$5:$R$204,2) -> 0 | K10: =COUNTIFS('Evaluación de riesgos'!$Q$5:$Q$204,1,'Evaluación de riesgos'!$R$5:$R$204,3) -> 1 | L10: =COUNTIFS('Evaluación de riesgos'!$Q$5:$Q$204,1,'Evaluación de riesgos'!$R$5:$R$204,4) -> 0 | M10: =COUNTIFS('Evaluación de riesgos'!$Q$5:$Q$204,1,'Evaluación de riesgos'!$R$5:$R$204,5) -> 0
A12: Resumen por nivel
A13: Nivel | B13: Inherente | C13: Residual
A14: Crítico | B14: =COUNTIF('Evaluación de riesgos'!$O$5:$O$204,A14) -> 2 | C14: =COUNTIF('Evaluación de riesgos'!$T$5:$T$204,A14) -> 0
A15: Alto | B15: =COUNTIF('Evaluación de riesgos'!$O$5:$O$204,A15) -> 2 | C15: =COUNTIF('Evaluación de riesgos'!$T$5:$T$204,A15) -> 0
A16: Medio | B16: =COUNTIF('Evaluación de riesgos'!$O$5:$O$204,A16) -> 1 | C16: =COUNTIF('Evaluación de riesgos'!$T$5:$T$204,A16) -> 3
A17: Bajo | B17: =COUNTIF('Evaluación de riesgos'!$O$5:$O$204,A17) -> 0 | C17: =COUNTIF('Evaluación de riesgos'!$T$5:$T$204,A17) -> 2
A18: Total | B18: =SUM(B14:B17) -> 5 | C18: =SUM(C14:C17) -> 5
A20: Riesgos residuales fuera del apetito | D20: =COUNTIF('Evaluación de riesgos'!$U$5:$U$204,"No*") -> 0
A21: Acciones de tratamiento vencidas | D21: =COUNTIF('Plan de tratamiento'!$M$5:$M$204,"Sí") -> 0

Sheet Escalas
A1: Escalas y criterios de evaluación
A2: Deben coincidir con PRO-01 §4.3 y §4.4.
A4: Valor | B4: Probabilidad | C4: Criterio
A5: 1 | B5: Muy baja | C5: Solo en circunstancias excepcionales; no ha ocurrido en la organización ni en el sector cercano
A6: 2 | B6: Baja | C6: Podría ocurrir alguna vez en los próximos 5 años
A7: 3 | B7: Media | C7: Podría ocurrir en los próximos 2 años, o ya ocurrió en organizaciones similares
A8: 4 | B8: Alta | C8: Probable en el próximo año, o ya ocurrió en la organización
A9: 5 | B9: Muy alta | C9: Ocurre o se espera varias veces al año
A11: Impacto
A12: Valor | B12: Impacto | C12: Financiero | D12: Operativo | E12: Legal / contractual | F12: Reputacional
A13: 1 | B13: Muy bajo | C13: < [$50,000] MXN | D13: Interrupción < 1 h sin efecto en clientes | E13: Ninguno | F13: Sin trascendencia externa
A14: 2 | B14: Bajo | C14: [$50,000 – $250,000] | D14: Interrupción de hasta 4 h | E14: Incumplimiento menor subsanable | F14: Queja aislada de un cliente
A15: 3 | B15: Medio | C15: [$250,000 – $1,000,000] | D15: Interrupción de hasta 1 día | E15: Penalización contractual | F15: Varios clientes afectados
A16: 4 | B16: Alto | C16: [$1,000,000 – $5,000,000] | D16: Interrupción de 1 a 3 días de servicios críticos | E16: Sanción de autoridad o demanda | F16: Cobertura en medios locales; pérdida de clientes
A17: 5 | B17: Muy alto | C17: > [$5,000,000] | D17: Más de 3 días o pérdida irrecuperable de información | E17: Sanción grave o suspensión | F17: Daño reputacional nacional o pérdida de clientes clave
A19: Niveles de riesgo (Probabilidad × Impacto)
A20: Desde | B20: Nivel | C20: Decisión | D20: Acepta el riesgo residual
A21: 1 | B21: Bajo | C21: Aceptable; se monitorea | D21: Propietario del riesgo
A22: 5 | B22: Medio | C22: Tratar si el costo es razonable | D22: Propietario + Responsable del SGSI
A23: 9 | B23: Alto | C23: Tratar; plan en ≤ 90 días | D23: Dirección General
A24: 15 | B24: Crítico | C24: Tratamiento inmediato; plan en ≤ 30 días | D24: Dirección General (excepcional, por escrito)
A25: Los valores de la columna Desde controlan la clasificación automática en la hoja Evaluación de riesgos.
A27: Apetito de riesgo: nivel residual máximo aceptable | D27: Medio
A28: Equivale a un nivel residual numérico máximo de: | D28: =IF(D27="Bajo",$A$22-1,IF(D27="Medio",$A$23-1,$A$24-1)) -> 8

Sheet Catálogo de amenazas
A1: Catálogo de amenazas
A2: Agrega amenazas al final de la lista; aparecerán en las listas desplegables.
A4: ID | B4: Amenaza | C4: Categoría | D4: Dimensión típica
A5: AM-01 | B5: Phishing e ingeniería social | C5: Humana deliberada | D5: C, I
A6: AM-02 | B6: Ransomware | C6: Software malicioso | D6: I, D
A7: AM-03 | B7: Otro software malicioso (troyanos, robo de información) | C7: Software malicioso | D7: C, I, D
A8: AM-04 | B8: Robo o compromiso de credenciales | C8: Humana deliberada | D8: C, I
A9: AM-05 | B9: Fraude por suplantación de correo (BEC) | C9: Humana deliberada | D9: I
A10: AM-06 | B10: Acceso no autorizado por personal interno o excolaboradores | C10: Humana deliberada | D10: C, I
A11: AM-07 | B11: Divulgación accidental de información | C11: Humana accidental | D11: C
A12: AM-08 | B12: Error humano en operación o configuración | C12: Humana accidental | D12: I, D
A13: AM-09 | B13: Explotación de vulnerabilidades técnicas | C13: Humana deliberada | D13: C, I, D
A14: AM-10 | B14: Ataque de denegación de servicio | C14: Humana deliberada | D14: D
A15: AM-11 | B15: Falla o interrupción de proveedor o servicio en la nube | C15: Proveedores | D15: D
... A34: AM-30 | B34: Toma de control de una cuenta privilegiada | C34: Humana deliberada | D34: C, I, D

Sheet Catálogo de vulnerabilidades
A1: Catálogo de vulnerabilidades
A2: Agrega vulnerabilidades al final de la lista; aparecerán en las listas desplegables.
A4: ID | B4: Vulnerabilidad
A5: VU-01 | B5: Ausencia de autenticación multifactor
A6: VU-02 | B6: Contraseñas débiles o reutilizadas
A7: VU-03 | B7: Falta de concientización del personal
A8: VU-04 | B8: Parches de seguridad no aplicados
A9: VU-05 | B9: Software o sistemas sin soporte del fabricante
A10: VU-06 | B10: Respaldos inexistentes, no probados o no aislados
A11: VU-07 | B11: Privilegios excesivos
A12: VU-08 | B12: Proceso de bajas de personal sin control
A13: VU-09 | B13: Equipos sin cifrado de disco
A14: VU-10 | B14: Configuraciones por defecto o no endurecidas
A15: VU-11 | B15: Falta de registro y monitoreo de eventos
... A34: VU-30 | B34: Sin lineamientos para el uso de IA generativa
